smart_url/__init__.py
smart_url/main.py
smart_url/utils.py
smart_url-1.0.1.dist-info/LICENSE
smart_url-1.0.1.dist-info/METADATA
smart_url-1.0.1.dist-info/WHEEL
smart_url-1.0.1.dist-info/top_level.txt
smart_url-1.0.1.dist-info/RECORD
