Metadata-Version: 2.1
Name: smart-url
Version: 1.0.1
Summary: Usefull path and url operations
Author-email: Gustavo Brito <britopereiragustavo@gmail.com>
License: MIT License        
Project-URL: Homepage, https://github.com/gustavobpereira/smart-url
Keywords: urllib,url,path
Classifier: License :: OSI Approved :: MIT License
Classifier: Programming Language :: Python
Classifier: Programming Language :: Python :: 3
Classifier: Topic :: Utilities
Requires-Python: >=3.9
License-File: LICENSE
